solver4mpi/__init__.py
solver4mpi/minimizer_multiprocess.py
solver4mpi/test.py
solver4mpi-2.2.dist-info/METADATA
solver4mpi-2.2.dist-info/WHEEL
solver4mpi-2.2.dist-info/top_level.txt
solver4mpi-2.2.dist-info/RECORD
