Metadata-Version: 2.1
Name: solver4mpi
Version: 2.2
Summary: Optimized minimizer for MPI python.
Home-page: https://github.com/mathias77515/optimized_minimizer
Author: Mathias Regnier
Author-email: mathias.p.regnier@gmail.com
Requires-Dist: multiprocess
